git_alert/__init__.py
git_alert/__main__.py
git_alert/argument_parser.py
git_alert/configuration.py
git_alert/display.py
git_alert/repositories.py
git_alert/traverse.py
git_alert/scripts/git_alert.py
git_alert-0.4.0.dist-info/METADATA
git_alert-0.4.0.dist-info/WHEEL
git_alert-0.4.0.dist-info/entry_points.txt
git_alert-0.4.0.dist-info/licenses/LICENSE
git_alert-0.4.0.dist-info/RECORD
