Metadata-Version: 2.4
Name: git_alert
Version: 0.4.0
Summary: Checks a given path and its sub-directories for dirty git repositories.
License: MIT License
License-File: LICENSE
Requires-Python: >=3.11.9
Requires-Dist: rich>=13.9.4
